[
	{ "s": "В", "p": [5, 14, 8, 4, 11, 9, 10, 3, 2, 13, 12, 7, 6, 1] },
	{ "s": "ВАРИАНТ", "p": [11] },
	{ "s": "ВВЕДИТЕ", "p": [10] },
	{ "s": "ВВЕРХУ", "p": [2] },
	{ "s": "ВВИДУ", "p": [12] },
	{ "s": "ВВОДА", "p": [10] },
	{ "s": "ВВОДИТЬ", "p": [10] },
	{ "s": "ВЕРНУТСЯ", "p": [8] },
	{ "s": "ВИД", "p": [2] },
	{ "s": "ВИДЕ", "p": [3] },
	{ "s": "ВИДИМОСТИ", "p": [14, 13] },
	{ "s": "ВИДИМОСТЬ", "p": [13] },
	{ "s": "ВНУТРЕННЕМУ", "p": [5] },
	{ "s": "ВО", "p": [12] },
	{ "s": "ВОЗЬМЕТСЯ", "p": [8] },
	{ "s": "ВОССТАНОВИТСЯ", "p": [14] },
	{ "s": "ВОССТАНОВЯТСЯ", "p": [14] },
	{ "s": "ВПЕРЕД", "p": [2] },
	{ "s": "ВРЕМЕНИ", "p": [4, 9, 11, 8, 3, 2, 1] },
	{ "s": "ВРЕМЯ", "p": [9, 8, 4, 3, 2, 1] },
	{ "s": "ВСЕ", "p": [2] },
	{ "s": "ВСЕМ", "p": [2] },
	{ "s": "ВСЕХ", "p": [14, 10] },
	{ "s": "ВСПЛЫВАЮЩЕМ", "p": [12, 11, 8] },
	{ "s": "ВЫ", "p": [5] },
	{ "s": "ВЫБОРА", "p": [2] },
	{ "s": "ВЫБРАН", "p": [8] },
	{ "s": "ВЫБРАННЫМ", "p": [4, 3] },
	{ "s": "ВЫБРАТЬ", "p": [12, 11, 10, 8, 3] },
	{ "s": "ВЫВОДЯТСЯ", "p": [11] },
	{ "s": "ВЫДАНО", "p": [5] },
	{ "s": "ВЫДЕЛЕНИЕ", "p": [2] },
	{ "s": "ВЫДЕЛЕННОГО", "p": [2] },
	{ "s": "ВЫДЕЛИТЬ", "p": [2] },
	{ "s": "ВЫДЕЛИТЬСЯ", "p": [10] },
	{ "s": "ВЫЗВАТЬ", "p": [2] },
	{ "s": "ВЫСОТА", "p": [14] },
	{ "s": "ВЫЧИСЛЯЕТСЯ", "p": [11, 4] }
]